{
  "doc_id": "7th Work Order_CPGRAMS PMU_DARPG_21102025",
  "meta": {
    "ministry": "Ministry of Personnel, Public Grievances and Pensions",
    "date": "2025-05-13",
    "value_inr": 3024000.0,
    "domains": [
      "Grievance Redressal",
      "Project Management"
    ],
    "project_subject": "Setting up of PMU for CPGRAMS with 3 resource persons for a",
    "doc_id": "7th Work Order_CPGRAMS PMU_DARPG_21102025"
  },
  "content": {
    "full_text": "S-15/17/2022-PG (C-1)-DARPG\nS-15/17/2022-PG(C-1)-DARPG(C.No.7620)\nGovernment of India\nMinistry of Personnel, Public Grievances and Pensions\nDepartment of Administrative Reforms and Public Grievances\n5th Floor, Sardar Patel Bhavan,\nSansad Marg, New Delhi\nDated\nOctober, 2025\n\u03a4\u03bf\nThe Secretary General\nQuality Council of India\nInstitute of Engineers\n2nd Floor, Bahadur Shah Zafar Marg\nNew Delhi-110001\nSubject: Setting up of PMU for CPGRAMS with 3 resource persons for a\nperiod beyond 30-9-25-Work Order-reg.\nSir,\nIn continuation of this Department's letter of even number dated 13-05-2025,\nI am directed to refer to the proposal received from Quality Council of India (QCI)\non the above subject and to convey the approval of the competent authority for\nextending the Work Order for setting up of Project Management Unit (PMU) of QCI\n(with three members) at a cost of Rs.30,24,000/- (excluding taxes), for a period of\n6 months (from 01-10-2025 to 31-03-2026) or till the implementation of NextGen\nCPGRAMS whichever is earlier subject to the terms and conditions (Deliverables\nand detailed plan of action) as specified below:-.\nDeliverables\ni. Review and streamlining existing categorization /taxonomy and mapping across\nthose Central Ministries/Departments that have volunteered by end of\nNovember, 2025.\nii. Target of review of root cause analysis as a time bound process of 4 month,\nincluding a review of the grievances/ disposal / feedback etc, covering about 85\nMinistries/Departments\niii Study of Public Grievances System for select Ministries/Departments and\nStates/UTs to understand the flow of grievances and bottlenecks as a time bound\nprocess of 4 months\niv. To prepare monthly reports on public grievances received on CPGRAMS on\nthe basis of multidimensional analysis with particular reference to performance of\nCentral Ministries and State Governments/ UTs by the 5th of each month with the\nlast acceptable date of 10 th of each month.\nv. To publish Annual Report on CPGRAMS every year by 2nd/3rd Week of\nDecember to enable the release during Good Governance Week Celebrations.\n1/3127/2025\nS-15/17/2022-PG (C-1)-DARPG\nvi. To make weekly, monthly presentations regarding review of CPGRAMS at\nSecretary, DARPG level and other higher authorities as desired by DARPG.\nvii. To assist DARPG in publicity & Communication strategy for CPGRAMS as well\nas on preparing any other reports / presentations/ IEC material as needed by it\nfrom time to time.\n'\nviii. To assist in the rollout of Next Gen CPGRAMS Chatbot and coordinate\nregarding the same\nix.Any Other work as assigned by DARPG from time to time\n2. This issue has the approval of the competent authority.\nPayment Milestones\n1. Completion of 1 months\n2. Completion of 2 months\n20%\n20%\n3. Completion of 3 months\n15%\n4. Completion of 4 months\n15%\n5. Completion of 5 months\n15%\n6. Completion of 6 months\nCopy to:-\nI. PPS to Secretary (DARPG)\nII. PSO to Addl. Secretary (DARPG)\nIII. Sr. Tech. Director, NIC\nIV. US(PG-Policy)\n15%\nYours faithfully,\nDigitally signed by\nD Parthasarathy Bhaskar\nDate: 21-10-2025\n(Parthasarathy Bhaskar)\nDeputy Secretary to the Govt. of India\n1/3127/2025\n",
    "deliverables": "Deliverables\nand detailed plan of action) as specified below:-.\nDeliverables\ni. Review and streamlining existing categorization /taxonomy and mapping across\nthose Central Ministries/Departments that have volunteered by end of\nNovember, 2025.\nii. Target of review of root cause analysis as a time bound process of 4 month,\nincluding a review of the grievances/ disposal / feedback etc, covering about 85\nMinistries/Departments\niii Study of Public Grievances System for select Ministries/Departments and\nStates/UTs to understand the flow of grievances and bottlenecks as a time bound\nprocess of 4 months\niv. To prepare monthly reports on public grievances received on CPGRAMS on\nthe basis of multidimensional analysis with particular reference to performance of\nCentral Ministries and State Governments/ UTs by the 5th of each month with the\nlast acceptable date of 10 th of each month.\nv. To publish Annual Report on CPGRAMS every year by 2nd/3rd Week of\nDecember to enable the release during Good Governance Week Celebrations.\n1/3127/2025\nS-15/17/2022-PG (C-1)-DARPG\nvi. To make weekly, monthly presentations regarding review of CPGRAMS at\nSecretary, DARPG level and other higher authorities as desired by DARPG.\nvii. To assist DARPG in publicity & Communication strategy for CPGRAMS as well\nas on preparing any other reports / presentations/ IEC material as needed by it\nfrom time to time.\n'\nviii. To assist in the rollout of Next Gen CPGRAMS Chatbot and coordinate\nregarding the same\nix.Any Other work as assigned by DARPG from time to time\n2. This issue has the approval of the competent authority.",
    "tables": []
  },
  "graph_nodes": []
}